{
    "configurations": [
        {
            "name": "Linux",
            "includePath": [
                "${workspaceFolder}/include/**",
                "/usr/lib/gcc/x86_64-pc-linux-gnu/13.2.1/include",
                "/usr/local/include",
                "/usr/lib/gcc/x86_64-pc-linux-gnu/13.2.1/include-fixed",
                "/usr/local/include",
                "/usr/include"
            ],
            "defines": [],
            "compilerPath": "/usr/bin/gcc",
            "cStandard": "c11",
            "cppStandard": "c++17",
            "intelliSenseMode": "linux-gcc-x64"
        },
        {
            "name": "Emscripten",
            "includePath": [
                "${workspaceFolder}/include/**",
                "/opt/emsdk/upstream/emscripten/system/include/**",
            ],
            "defines": ["__EMSCRIPTEN__"],
            "compilerPath": "/usr/bin/gcc",
            "cStandard": "c11",
            "cppStandard": "c++17",
            "intelliSenseMode": "linux-gcc-x64"
        }

    ],
    "version": 4
}
